LICENSE.txt
README.md
setup.cfg
setup.py
dbfilters/src/binaryfuse8.h
dbfilters/src/binaryfuse_wrapper.c
dbfilters/src/hex_avx2.h
dbfilters/src/preprocess.h
dbfilters/src/preprocess_wrapper.c
dbfilters/src/ribbon128_avx2.h
dbfilters/src/ribbon_wrapper.c
dbfilters/src/sha1-avx.S
dbfilters/src/sha1.h
dbfilters/src/shishua.h
dbfilters/src/splitblockbloom.h
dbfilters/src/splitblockbloom_wrapper.c
dbfilters/src/utils.h
dbfilters/src/utils_wrapper.c
dbfilters/src/xor16.h
dbfilters/src/xor16_wrapper.c
dbfilters/src/xor8.h
dbfilters/src/xor8_wrapper.c
django_pwnedpass_validator.egg-info/PKG-INFO
django_pwnedpass_validator.egg-info/SOURCES.txt
django_pwnedpass_validator.egg-info/dependency_links.txt
django_pwnedpass_validator.egg-info/requires.txt
django_pwnedpass_validator.egg-info/top_level.txt
filterclient/__init__.py
filterclient/admin.py
filterclient/apps.py
filterclient/models.py
filterclient/settings.py
filterclient/tests.py
filterclient/validators.py
filterclient/views.py
filterclient/management/commands/__init__.py
filterclient/management/commands/preprocess.py
filterclient/management/commands/purge.py
filterclient/management/commands/test.py
filterclient/migrations/__init__.py
filterserver/__init__.py
filterserver/admin.py
filterserver/apps.py
filterserver/models.py
filterserver/settings.py
filterserver/tests.py
filterserver/urls.py
filterserver/views.py
filterserver/management/commands/__init__.py
filterserver/management/commands/test.py
filterserver/migrations/__init__.py